setup.py
contextlayers/__init__.py
contextlayers/admin.py
contextlayers/context_processors.py
contextlayers/managers.py
contextlayers/models.py
django_contextlayers.egg-info/PKG-INFO
django_contextlayers.egg-info/SOURCES.txt
django_contextlayers.egg-info/dependency_links.txt
django_contextlayers.egg-info/top_level.txt