Metadata-Version: 1.0
Name: django-contextlayers
Version: 0.1
Summary: Slather your templates with contextual data.
Home-page: https://github.com/natural/django-contextlayers
Author: Troy Melhase
Author-email: troy@troy.io
License: BSD License
Platform: UNKNOWN
Classifier: Environment :: Web Environment
Classifier: Framework :: Django
Classifier: Intended Audience :: Developers
Classifier: License :: OSI Approved :: BSD License
Classifier: Operating System :: OS Independent
Classifier: Programming Language :: Python
Classifier: Programming Language :: Python :: 2.6
Classifier: Programming Language :: Python :: 2.7
Classifier: Topic :: Internet :: WWW/HTTP
Classifier: Topic :: Internet :: WWW/HTTP :: Dynamic Content
